Metadata-Version: 2.1
Name: tyfabu
Version: 1.0.0
Summary: this is a niubi lib
Home-page: https://github.com/ty/python_code
Author: ty
Author-email: 1003144926@qq.com
License-File: LICENSE.txt
